vasp_manager/__init__.py
vasp_manager/job_manager.py
vasp_manager/py.typed
vasp_manager/types.py
vasp_manager/utils.py
vasp_manager/vasp_input_creator.py
vasp_manager/vasp_manager.py
vasp_manager/analyzer/__init__.py
vasp_manager/analyzer/bulkmod_analyzer.py
vasp_manager/analyzer/elastic_analyzer.py
vasp_manager/calculation_manager/__init__.py
vasp_manager/calculation_manager/base.py
vasp_manager/calculation_manager/bulkmod.py
vasp_manager/calculation_manager/elastic.py
vasp_manager/calculation_manager/rlx.py
vasp_manager/calculation_manager/rlx_coarse.py
vasp_manager/calculation_manager/static.py
vasp_manager/static_files/INCAR_template
vasp_manager/static_files/__init__.py
vasp_manager/static_files/d_f_block.json
vasp_manager/static_files/hubbards.json
vasp_manager/static_files/pot_dict.json
vasp_manager/static_files/pot_dict_52.json
vasp_manager/static_files/pot_dict_54.json
vasp_manager/static_files/pot_dict_oqmd.json
vasp_manager/static_files/q_handles.json
vasp_manager/static_files/vasp-bridges2.yml
vasp_manager/static_files/vasp-bulkmod-bridges2.yml
vasp_manager/static_files/vasp-bulkmod-quest.yml
vasp_manager/static_files/vasp-bulkmod.yml
vasp_manager/static_files/vasp-quest.yml
vasp_manager/static_files/vasp.q
vasp_manager/static_files/vasp.yml
vasp_manager/tests/__init__.py
vasp_manager/tests/test_analyzers.py
vasp_manager/tests/test_calculation_managers.py
vasp_manager/tests/test_utils.py
vasp_manager/tests/test_vasp_manager.py
vasp_manager/tests/POTCARS/POTCAR_example
vasp_manager/tests/POTCARS/Cl/POTCAR
vasp_manager/tests/POTCARS/Cu/POTCAR
vasp_manager/tests/POTCARS/Na_pv/POTCAR
vasp_manager/tests/POTCARS/O/POTCAR
vasp_manager/tests/calculations/calc_config.json
vasp_manager/tests/calculations/computing_config.json
vasp_manager/tests/calculations/material/POSCAR
vasp_manager/tests/calculations/material/bulkmod/INCAR
vasp_manager/tests/calculations/material/bulkmod/POSCAR
vasp_manager/tests/calculations/material/bulkmod/POTCAR
vasp_manager-1.4.2.dist-info/licenses/LICENSE.md
vasp_manager-1.4.2.dist-info/METADATA
vasp_manager-1.4.2.dist-info/WHEEL
vasp_manager-1.4.2.dist-info/top_level.txt
vasp_manager-1.4.2.dist-info/RECORD
