Metadata-Version: 2.4
Name: vasp_manager
Version: 1.4.2
Summary: A simple package to run and analyze VASP calculations
Author-email: Dale Gaines II <dalegainesii@gmail.com>
Maintainer-email: Dale Gaines II <dalegainesii@gmail.com>
License-Expression: MIT
Project-URL: repository, https://github.com/dgaines2/vasp_manager
Keywords: vasp,dft,high-throughput
Requires-Python: >=3.10.0
License-File: LICENSE.md
Requires-Dist: pymatgen>=2022.5
Requires-Dist: importlib_resources
Provides-Extra: dev
Requires-Dist: black; extra == "dev"
Requires-Dist: coverage; extra == "dev"
Requires-Dist: isort; extra == "dev"
Requires-Dist: pre-commit; extra == "dev"
Requires-Dist: pytest; extra == "dev"
Requires-Dist: mypy; extra == "dev"
Provides-Extra: docs
Requires-Dist: blacken-docs>=1.16.0; extra == "docs"
Requires-Dist: mkdocs-material>=9.5.16; extra == "docs"
Requires-Dist: mkdocstrings[python]>=0.22.0; extra == "docs"
Requires-Dist: mkdocs-gen-files>=0.5.0; extra == "docs"
Requires-Dist: mkdocs-literate-nav>=0.6.0; extra == "docs"
Requires-Dist: pillow>=10.0.0; extra == "docs"
Dynamic: license-file
